MANIFEST.in
README.md
requirements.txt
setup.py
ixau_pyexos.egg-info/PKG-INFO
ixau_pyexos.egg-info/SOURCES.txt
ixau_pyexos.egg-info/dependency_links.txt
ixau_pyexos.egg-info/requires.txt
ixau_pyexos.egg-info/top_level.txt
pyexos/__init__.py
pyexos/exos.py
pyexos/utils.py